Workbook

Sheet Project Guide
A1: Velora Athletics — 3-Year Financial Forecast & Valuation Model
A2: Excel portfolio case study | Historical FY2024–FY2026 | Forecast FY2027–FY2029
A4: Project Objective
A5: Build a simplified three-year operating forecast for Velora Athletics and estimate an implied share price using a P/E multiple. The model is driven by Bear, Base, and Bull assumptions for revenue growth, gross margin, SG&A intensity, tax rate, share count, and valuation multiple.
A10: Workbook Structure | D10: Finance Modeling Color Key
A11: Sheet | B11: Purpose | D11: Color | E11: Meaning
A12: Raw Data | B12: Synthetic FY2024–FY2026 Velora Athletics financial inputs | D12: Blue text | E12: Hardcoded inputs / assumptions
A13: Assumptions | B13: Bear/Base/Bull scenario drivers and scenario selector | D13: Green text | E13: Links to another worksheet
A14: Forecast & Valuation | B14: Historical analysis, 3-year forecast, EPS, and P/E valuation | D14: Black text | E14: Formulas calculated on the current sheet
A15: Dashboard | B15: Key forecast outputs, valuation sensitivity, and charts
A16: Formula Guide | B16: Reference formulas for rebuilding or explaining the model

Sheet Raw Data
A1: Velora Athletics Historical Financial Data
A2: Synthetic Velora Athletics case-study data | Fiscal 2024–2026 | $ in millions except per-share data
A4: Metric | B4: FY2024A | C4: FY2025A | D4: FY2026A | E4: Units
A5: Revenue | B5: 49800 | C5: 47250 | D5: 48100 | E5: $mm
A6: Cost of Sales | B6: 27650 | C6: 26800 | D6: 27100 | E6: $mm
A7: Gross Profit | B7: 22150 | C7: 20450 | D7: 21000 | E7: $mm
A8: Demand Creation Expense | B8: 4200 | C8: 4450 | D8: 4525 | E8: $mm
A9: Operating Overhead Expense | B9: 11900 | C9: 11450 | D9: 11525 | E9: $mm
A10: Total SG&A Expense | B10: 16100 | C10: 15900 | D10: 16050 | E10: $mm
A11: Interest Expense (Income), Net | B11: -90 | C11: -70 | D11: -40 | E11: $mm
A12: Other (Income) Expense, Net | B12: -160 | C12: -60 | D12: -45 | E12: $mm
A13: Income Before Income Taxes | B13: 6300 | C13: 4680 | D13: 5035 | E13: $mm
A14: Income Tax Expense | B14: 1103 | C14: 842 | D14: 1007 | E14: $mm
A15: Net Income | B15: 5197 | C15: 3838 | D15: 4028 | E15: $mm
A16: Diluted EPS | B16: 3.46 | C16: 2.61 | D16: 2.8 | E16: $ / share
A17: Diluted Weighted Avg. Shares | B17: 1500 | C17: 1470 | D17: 1440 | E17: mm shares

Sheet Assumptions
A1: Velora Athletics Scenario Assumptions
A2: Change B3 to Bear, Base, or Bull. Blue cells are editable inputs.
A3: Selected Scenario | B3: Base
A5: Scenario Table
A6: Scenario | B6: FY27 Rev Growth | C6: FY28 Rev Growth | D6: FY29 Rev Growth | E6: FY27 Gross Margin | F6: FY28 Gross Margin | G6: FY29 Gross Margin | H6: FY27 SG&A % Rev | I6: FY28 SG&A % Rev | J6: FY29 SG&A % Rev | K6: Tax Rate | L6: P/E Multiple | M6: Annual Share Change | N6: Net Other Income % Rev
A7: Bear | B7: -0.02 | C7: 0.01 | D7: 0.03 | E7: 0.42 | F7: 0.423 | G7: 0.427 | H7: 0.355 | I7: 0.352 | J7: 0.348 | K7: 0.215 | L7: 18 | M7: -0.003 | N7: 0.001
A8: Base | B8: 0.035 | C8: 0.05 | D8: 0.06 | E8: 0.433 | F8: 0.44 | G8: 0.445 | H8: 0.342 | I8: 0.338 | J8: 0.334 | K8: 0.205 | L8: 24 | M8: -0.008 | N8: 0.002
A9: Bull | B9: 0.07 | C9: 0.08 | D9: 0.07 | E9: 0.445 | F9: 0.455 | G9: 0.46 | H9: 0.33 | I9: 0.325 | J9: 0.32 | K9: 0.195 | L9: 30 | M9: -0.012 | N9: 0.003
A11: Selected Scenario Output | F11: Selected Operating Assumptions
A12: Assumption | B12: Selected Value | F12: Metric | G12: FY2027E | H12: FY2028E | I12: FY2029E | J12: Notes
A13: FY2027 Revenue Growth | B13: =IF($B$3="Bear",B7,IF($B$3="Base",B8,B9)) -> 0.035 | F13: Gross Margin | G13: =IF($B$3="Bear",E7,IF($B$3="Base",E8,E9)) -> 0.433 | H13: =IF($B$3="Bear",F7,IF($B$3="Base",F8,F9)) -> 0.44 | I13: =IF($B$3="Bear",G7,IF($B$3="Base",G8,G9)) -> 0.445 | J13: Gross Profit / Revenue
A14: FY2028 Revenue Growth | B14: =IF($B$3="Bear",C7,IF($B$3="Base",C8,C9)) -> 0.05 | F14: SG&A % Revenue | G14: =IF($B$3="Bear",H7,IF($B$3="Base",H8,H9)) -> 0.342 | H14: =IF($B$3="Bear",I7,IF($B$3="Base",I8,I9)) -> 0.338 | I14: =IF($B$3="Bear",J7,IF($B$3="Base",J8,J9)) -> 0.334 | J14: Total SG&A / Revenue
A15: FY2029 Revenue Growth | B15: =IF($B$3="Bear",D7,IF($B$3="Base",D8,D9)) -> 0.06 | F15: Revenue Growth | G15: =IF($B$3="Bear",B7,IF($B$3="Base",B8,B9)) -> 0.035 | H15: =IF($B$3="Bear",C7,IF($B$3="Base",C8,C9)) -> 0.05 | I15: =IF($B$3="Bear",D7,IF($B$3="Base",D8,D9)) -> 0.06 | J15: Year-over-year growth
A16: Tax Rate | B16: =IF($B$3="Bear",K7,IF($B$3="Base",K8,K9)) -> 0.205
A17: P/E Multiple | B17: =IF($B$3="Bear",L7,IF($B$3="Base",L8,L9)) -> 24
A18: Annual Share Change | B18: =IF($B$3="Bear",M7,IF($B$3="Base",M8,M9)) -> -0.008
A19: Net Other Income % Revenue | B19: =IF($B$3="Bear",N7,IF($B$3="Base",N8,N9)) -> 0.002

Sheet Forecast & Valuation
A1: Velora Athletics Forecast & Valuation
A2: Historical results linked from Raw Data; forecasts driven by Assumptions
A4: Metric | B4: FY2024A | C4: FY2025A | D4: FY2026A | E4: FY2027E | F4: FY2028E | G4: FY2029E
A5: Revenue | B5: ='Raw Data'!B5 -> 49800 | C5: ='Raw Data'!C5 -> 47250 | D5: ='Raw Data'!D5 -> 48100 | E5: =D5*(1+E6) -> 49783.5 | F5: =E5*(1+F6) -> 52272.675 | G5: =F5*(1+G6) -> 55409.035
A6: Revenue Growth | C6: =C5/B5-1 -> -0.051204819 | D6: =D5/C5-1 -> 0.017989418 | E6: =Assumptions!B13 -> 0.035 | F6: =Assumptions!B14 -> 0.05 | G6: =Assumptions!B15 -> 0.06
A7: Gross Profit | B7: ='Raw Data'!B7 -> 22150 | C7: ='Raw Data'!C7 -> 20450 | D7: ='Raw Data'!D7 -> 21000 | E7: =E5*E8 -> 21556.255 | F7: =F5*F8 -> 22999.977 | G7: =G5*G8 -> 24657.021
A8: Gross Margin | B8: =B7/B5 -> 0.44477912 | C8: =C7/C5 -> 0.43280423 | D8: =D7/D5 -> 0.43659044 | E8: =Assumptions!G13 -> 0.433 | F8: =Assumptions!H13 -> 0.44 | G8: =Assumptions!I13 -> 0.445
A9: Total SG&A | B9: ='Raw Data'!B10 -> 16100 | C9: ='Raw Data'!C10 -> 15900 | D9: ='Raw Data'!D10 -> 16050 | E9: =E5*E10 -> 17025.957 | F9: =F5*F10 -> 17668.164 | G9: =G5*G10 -> 18506.618
A10: SG&A % Revenue | B10: =B9/B5 -> 0.32329317 | C10: =C9/C5 -> 0.33650794 | D10: =D9/D5 -> 0.33367983 | E10: =Assumptions!G14 -> 0.342 | F10: =Assumptions!H14 -> 0.338 | G10: =Assumptions!I14 -> 0.334
A11: Operating Income | B11: =B7-B9 -> 6050 | C11: =C7-C9 -> 4550 | D11: =D7-D9 -> 4950 | E11: =E7-E9 -> 4530.2985 | F11: =F7-F9 -> 5331.8128 | G11: =G7-G9 -> 6150.4029
A12: Operating Margin | B12: =B11/B5 -> 0.12148594 | C12: =C11/C5 -> 0.096296296 | D12: =D11/D5 -> 0.1029106 | E12: =E11/E5 -> 0.091 | F12: =F11/F5 -> 0.102 | G12: =G11/G5 -> 0.111
A13: Net Interest & Other Income | B13: =-('Raw Data'!B11+'Raw Data'!B12) -> 250 | C13: =-('Raw Data'!C11+'Raw Data'!C12) -> 130 | D13: =-('Raw Data'!D11+'Raw Data'!D12) -> 85 | E13: =E5*Assumptions!B19 -> 99.567 | F13: =F5*Assumptions!B19 -> 104.54535 | G13: =G5*Assumptions!B19 -> 110.81807
A14: Income Before Taxes | B14: ='Raw Data'!B13 -> 6300 | C14: ='Raw Data'!C13 -> 4680 | D14: ='Raw Data'!D13 -> 5035 | E14: =E11+E13 -> 4629.8655 | F14: =F11+F13 -> 5436.3582 | G14: =G11+G13 -> 6261.221
A15: Tax Rate | B15: =B16/B14 -> 0.17507937 | C15: =C16/C14 -> 0.17991453 | D15: =D16/D14 -> 0.2 | E15: =Assumptions!B16 -> 0.205 | F15: =Assumptions!B16 -> 0.205 | G15: =Assumptions!B16 -> 0.205
A16: Income Tax Expense | B16: ='Raw Data'!B14 -> 1103 | C16: ='Raw Data'!C14 -> 842 | D16: ='Raw Data'!D14 -> 1007 | E16: =E14*E15 -> 949.12243 | F16: =F14*F15 -> 1114.4534 | G16: =G14*G15 -> 1283.5503
A17: Net Income | B17: ='Raw Data'!B15 -> 5197 | C17: ='Raw Data'!C15 -> 3838 | D17: ='Raw Data'!D15 -> 4028 | E17: =E14-E16 -> 3680.7431 | F17: =F14-F16 -> 4321.9048 | G17: =G14-G16 -> 4977.6707
A18: Net Margin | B18: =B17/B5 -> 0.10435743 | C18: =C17/C5 -> 0.081227513 | D18: =D17/D5 -> 0.083742204 | E18: =E17/E5 -> 0.073935 | F18: =F17/F5 -> 0.08268 | G18: =G17/G5 -> 0.089835
A19: Diluted Shares | B19: ='Raw Data'!B17 -> 1500 | C19: ='Raw Data'!C17 -> 1470 | D19: ='Raw Data'!D17 -> 1440 | E19: =D19*(1+Assumptions!B18) -> 1428.48 | F19: =E19*(1+Assumptions!B18) -> 1417.0522 | G19: =F19*(1+Assumptions!B18) -> 1405.7157
A20: Diluted EPS | B20: ='Raw Data'!B16 -> 3.46 | C20: ='Raw Data'!C16 -> 2.61 | D20: ='Raw Data'!D16 -> 2.8 | E20: =E17/E19 -> 2.5766851 | F20: =F17/F19 -> 3.0499264 | G20: =G17/G19 -> 3.5410222
A21: P/E Multiple | E21: =Assumptions!B17 -> 24 | F21: =Assumptions!B17 -> 24 | G21: =Assumptions!B17 -> 24
A22: Implied Share Price | E22: =E20*E21 -> 61.840441 | F22: =F20*F21 -> 73.198233 | G22: =G20*G21 -> 84.984534

Sheet Dashboard
A1: Velora Athletics Financial Model Dashboard
A2: Scenario-driven forecast and simple P/E valuation summary
A4: Selected Scenario | B4: =Assumptions!B3 -> Base
A6: FY2029E Revenue | B6: ='Forecast & Valuation'!G5 -> 55409.035
A7: FY2029E Net Income | B7: ='Forecast & Valuation'!G17 -> 4977.6707
A8: FY2029E EPS | B8: ='Forecast & Valuation'!G20 -> 3.5410222
A9: P/E Multiple | B9: ='Forecast & Valuation'!G21 -> 24
A10: FY2029E Implied Price | B10: ='Forecast & Valuation'!G22 -> 84.984534
A11: Revenue CAGR (FY26–FY29) | B11: =('Forecast & Valuation'!G5/'Forecast & Valuation'!D5)^(1/3)-1 -> 0.048282908
A14: Series | B14: FY2024A | C14: FY2025A | D14: FY2026A | E14: FY2027E | F14: FY2028E | G14: FY2029E
A15: Revenue | B15: ='Forecast & Valuation'!B5 -> 49800 | C15: ='Forecast & Valuation'!C5 -> 47250 | D15: ='Forecast & Valuation'!D5 -> 48100 | E15: ='Forecast & Valuation'!E5 -> 49783.5 | F15: ='Forecast & Valuation'!F5 -> 52272.675 | G15: ='Forecast & Valuation'!G5 -> 55409.035
A18: Series | B18: FY2024A | C18: FY2025A | D18: FY2026A | E18: FY2027E | F18: FY2028E | G18: FY2029E
A19: Net Income | B19: ='Forecast & Valuation'!B17 -> 5197 | C19: ='Forecast & Valuation'!C17 -> 3838 | D19: ='Forecast & Valuation'!D17 -> 4028 | E19: ='Forecast & Valuation'!E17 -> 3680.7431 | F19: ='Forecast & Valuation'!F17 -> 4321.9048 | G19: ='Forecast & Valuation'!G17 -> 4977.6707
A22: FY2029E P/E Sensitivity
A23: P/E Multiple | B23: FY2029E EPS | C23: Implied Price
A24: 16 | B24: ='Forecast & Valuation'!G20 -> 3.5410222 | C24: =A24*B24 -> 56.656356
A25: 20 | B25: ='Forecast & Valuation'!G20 -> 3.5410222 | C25: =A25*B25 -> 70.820445
A26: 24 | B26: ='Forecast & Valuation'!G20 -> 3.5410222 | C26: =A26*B26 -> 84.984534
A27: 28 | B27: ='Forecast & Valuation'!G20 -> 3.5410222 | C27: =A27*B27 -> 99.148623
A28: 32 | B28: ='Forecast & Valuation'!G20 -> 3.5410222 | C28: =A28*B28 -> 113.31271

Sheet Formula Guide
A1: Formula Guide
A2: Reference formulas for rebuilding the model yourself.
A4: Historical Analysis
A5: Metric | B5: Example Excel Formula | C5: What It Measures | D5: Suggested Source | E5: Output Format | F5: Notes
A6: Revenue Growth | B6: =Current Year Revenue / Prior Year Revenue - 1 | C6: Year-over-year change in sales | D6: Raw Data | E6: % | F6: First historical year has no prior-year growth.
A7: Gross Margin | B7: =Gross Profit / Revenue | C7: Gross profit earned per dollar of revenue | D7: Raw Data | E7: %
A8: SG&A % Revenue | B8: =Total SG&A / Revenue | C8: Operating expense intensity | D8: Raw Data | E8: %
A9: Operating Income | B9: =Gross Profit - Total SG&A | C9: Operating profit before interest/other items and taxes | D9: Calculated | E9: $mm
A10: Operating Margin | B10: =Operating Income / Revenue | C10: Operating profitability | D10: Calculated | E10: %
A11: Tax Rate | B11: =Income Tax Expense / Income Before Taxes | C11: Effective tax rate | D11: Raw Data | E11: %
A12: Net Margin | B12: =Net Income / Revenue | C12: Net profitability | D12: Raw Data | E12: %
A14: Forecast & Valuation Formulas
A15: Metric | B15: Example Excel Formula | C15: Purpose | D15: Driver | E15: Output Format | F15: Build Tip
A16: Forecast Revenue | B16: =Prior Year Revenue*(1+Revenue Growth) | C16: Projects annual sales | D16: Scenario revenue growth | E16: $mm | F16: Link growth rate from Assumptions.
A17: Forecast Gross Profit | B17: =Revenue*Gross Margin | C17: Projects gross profit | D17: Scenario gross margin | E17: $mm | F17: Use selected scenario margin.
A18: Forecast SG&A | B18: =Revenue*SG&A % Revenue | C18: Projects selling/admin costs | D18: Scenario SG&A % | E18: $mm
A19: Operating Income | B19: =Gross Profit-SG&A | C19: Projects operating profit | D19: Forecast GP and SG&A | E19: $mm
A20: Net Interest & Other Income | B20: =Revenue*Net Other Income % Revenue | C20: Simplified non-operating item | D20: Scenario assumption | E20: $mm
A21: Income Before Taxes | B21: =Operating Income+Net Interest & Other Income | C21: Projects pretax earnings | D21: Calculated | E21: $mm
A22: Income Tax Expense | B22: =Income Before Taxes*Tax Rate | C22: Projects taxes | D22: Scenario tax rate | E22: $mm
A23: Net Income | B23: =Income Before Taxes-Income Tax Expense | C23: Projects bottom-line earnings | D23: Calculated | E23: $mm
A24: Diluted Shares | B24: =Prior Year Shares*(1+Annual Share Change) | C24: Projects share count | D24: Scenario share change | E24: mm shares
A25: Diluted EPS | B25: =Net Income/Diluted Shares | C25: Earnings per diluted share | D25: Calculated | E25: $ / share
A26: Implied Share Price | B26: =Diluted EPS*P/E Multiple | C26: Simple P/E-based valuation | D26: Scenario P/E multiple | E26: $ / share
A28: Modeling convention: blue text represents hardcoded inputs, green text represents links to other worksheets, and black text represents formulas calculated on the current worksheet. The formulas above are examples; your exact cell references depend on where you build the Forecast sheet.
